yaeuvm/__init__.py
yaeuvm/_misc.py
yaeuvm/_yaeuvm_ba.py
yaeuvm/_yaeuvm_br.py
yaeuvm/_yaeuvm_r.py
yaeuvm/_coeffs/_yaeuvm_ba_coeffs.nc
yaeuvm/_coeffs/_yaeuvm_br_coeffs.nc
yaeuvm/_coeffs/_yaeuvm_r_coeffs.nc
yaeuvm-0.0.4b0.dist-info/licenses/LICENSE.txt
yaeuvm-0.0.4b0.dist-info/METADATA
yaeuvm-0.0.4b0.dist-info/WHEEL
yaeuvm-0.0.4b0.dist-info/top_level.txt
yaeuvm-0.0.4b0.dist-info/RECORD
