Metadata-Version: 2.4
Name: yaeuvm
Version: 0.0.4b0
Author-email: Anton Tatarnikov <tatarnikoffanton@yandex.ru>, Oleg Zolotov <ovz.office@gmail.com>
License-Expression: Apache-2.0
Project-URL: Homepage, https://github.com/klklklo/yaeuvm
Classifier: Development Status :: 4 - Beta
Classifier: Intended Audience :: Science/Research
Classifier: Programming Language :: Python :: 3
Classifier: Programming Language :: Python :: 3.7
Classifier: Programming Language :: Python :: 3.8
Classifier: Programming Language :: Python :: 3.9
Classifier: Programming Language :: Python :: 3.10
Classifier: Programming Language :: Python :: 3.11
Classifier: Topic :: Scientific/Engineering :: Physics
Requires-Python: >=3.7
License-File: LICENSE.txt
Requires-Dist: importlib-resources
Requires-Dist: netcdf4
Requires-Dist: numpy
Requires-Dist: pandas
Requires-Dist: xarray
Dynamic: license-file
